django_redis_session_store/__init__.py
django_redis_session_store/redis_server.py
django_redis_session_store/session_store.py
django_redis_session_store/tests.py
django_redis_session_store-0.1.1.dist-info/LICENSE
django_redis_session_store-0.1.1.dist-info/METADATA
django_redis_session_store-0.1.1.dist-info/WHEEL
django_redis_session_store-0.1.1.dist-info/top_level.txt
django_redis_session_store-0.1.1.dist-info/RECORD
